{"rowCount":5,"colCount":5,"type":0,"letters":"أدشقم","words":[{"word":"أشد","vertical":true,"rowIndex":2,"colIndex":1,"coinIndices":[],"awardCoins":false},{"word":"أقدم","vertical":false,"rowIndex":2,"colIndex":1,"coinIndices":[],"awardCoins":false},{"word":"دمشق","vertical":true,"rowIndex":1,"colIndex":4,"coinIndices":[],"awardCoins":false},{"word":"أمد","vertical":false,"rowIndex":0,"colIndex":1,"coinIndices":[],"awardCoins":false},{"word":"مدق","vertical":true,"rowIndex":0,"colIndex":2,"coinIndices":[],"awardCoins":false},{"word":"قدم","vertical":false,"rowIndex":4,"colIndex":0,"coinIndices":[],"awardCoins":false}],"id":"3d45efa41458c1e626d02b6c0d06108c"}